README.md
setup.py
aio_timers/__init__.py
aio_timers/__main__.py
aio_timers/version.py
aio_timers.egg-info/PKG-INFO
aio_timers.egg-info/SOURCES.txt
aio_timers.egg-info/dependency_links.txt
aio_timers.egg-info/top_level.txt