Metadata-Version: 2.1
Name: aio-timers
Version: 0.0.1
Summary: Timer support for asyncio.
Home-page: https://github.com/ThierrySpetebroot/aio-timers
Author: Thierry Spetebroot <thierry.spetebroot@gmail.com>
Author-email: thierry.spetebroot@gmail.com
License: MIT License
Platform: all
Classifier: Programming Language :: Python :: 3
Classifier: Programming Language :: Python :: 3.5
Classifier: Programming Language :: Python :: 3.6
Classifier: Programming Language :: Python :: 3.7
Classifier: Programming Language :: Python :: 3 :: Only
Classifier: Framework :: AsyncIO
Classifier: Intended Audience :: Developers
Classifier: License :: OSI Approved :: MIT License
Classifier: Operating System :: OS Independent
Requires-Python: >=3.5.*, <4
